for_adp/__init__.py
for_adp/aa.py
for_adp/bb.py
for_adp/m10.py
for_adp/m11.py
for_adp/m12.py
for_adp/m13.py
for_adp/m14.py
for_adp/m18.py
for_adp/m19.py
for_adp/m2.py
for_adp/m20.py
for_adp/m21.py
for_adp/m22.py
for_adp/m23.py
for_adp/m24.py
for_adp/m25.py
for_adp/m26.py
for_adp/m27.py
for_adp/m28.py
for_adp/m29.py
for_adp/m3.py
for_adp/m30.py
for_adp/m4.py
for_adp/m5.py
for_adp/m6.py
for_adp/m7.py
for_adp/m8.py
for_adp/m9.py
for_adp/qq.py
for_adp/s11_1.py
for_adp/s11_2.py
for_adp/s2.py
for_adp/s3.py
for_adp/s4.py
for_adp/s5.py
for_adp/s6.py
for_adp/s7.py
for_adp/s8.py
for_adp/s910.py
for_adp/time.py
for_adp-0.0.12.dist-info/METADATA
for_adp-0.0.12.dist-info/WHEEL
for_adp-0.0.12.dist-info/top_level.txt
for_adp-0.0.12.dist-info/RECORD
