Metadata-Version: 2.1
Name: for-adp
Version: 0.0.12
Summary: adp_code
Home-page: 
Author: tofir
Author-email: wg7221@naver.com
Requires-Python: >=2.7
